openai_streamer/__init__.py
openai_streamer/example.py
openai_streamer/streamer.py
openai_streamer-0.1.0.dist-info/LICENSE
openai_streamer-0.1.0.dist-info/METADATA
openai_streamer-0.1.0.dist-info/WHEEL
openai_streamer-0.1.0.dist-info/top_level.txt
openai_streamer-0.1.0.dist-info/RECORD
