Metadata-Version: 2.2
Name: openai-streamer
Version: 0.1.0
Summary: A package for streaming text completion using OpenAI's Responses API
Home-page: https://github.com/yourusername/openai-streamer
Author: Serge
Author-email: your.email@example.com
Project-URL: Bug Tracker, https://github.com/yourusername/openai-streamer/issues
Keywords: openai,ai,streaming,text completion,gpt
Classifier: Programming Language :: Python :: 3
Classifier: License :: OSI Approved :: MIT License
Classifier: Operating System :: OS Independent
Classifier: Development Status :: 4 - Beta
Classifier: Intended Audience :: Developers
Classifier: Topic :: Software Development :: Libraries :: Python Modules
Requires-Python: >=3.8
License-File: LICENSE
Requires-Dist: openai>=1.0.0
Requires-Dist: python-dotenv>=0.19.0
Dynamic: author
Dynamic: author-email
Dynamic: classifier
Dynamic: description
Dynamic: description-content-type
Dynamic: home-page
Dynamic: keywords
Dynamic: project-url
Dynamic: requires-dist
Dynamic: requires-python
Dynamic: summary
